{"id":"2083","name":"シュヴァリエ","eps":[{"id":11699,"name":"デオン∴リア","sites":[{"site":"bilibili","title":"迪恩∴莉雅","url":"https://www.bilibili.com/bangumi/play/ep70020"}]},{"id":11700,"name":"四銃士","sites":[{"site":"bilibili","title":"四剑客","url":"https://www.bilibili.com/bangumi/play/ep70030"}]},{"id":11701,"name":"悲憤の剣","sites":[{"site":"bilibili","title":"悲愤之剑","url":"https://www.bilibili.com/bangumi/play/ep70056"}]},{"id":11702,"name":"革命の信徒","sites":[{"site":"bilibili","title":"革命的信徒","url":"https://www.bilibili.com/bangumi/play/ep70130"}]},{"id":11703,"name":"パレ・ロワイヤル","sites":[{"site":"bilibili","title":"巴黎皇家宫殿","url":"https://www.bilibili.com/bangumi/play/ep70131"}]},{"id":11704,"name":"王の騎士","sites":[{"site":"bilibili","title":"王之骑士","url":"https://www.bilibili.com/bangumi/play/ep70108"}]},{"id":11705,"name":"ガーゴイル","sites":[{"site":"bilibili","title":"石像怪","url":"https://www.bilibili.com/bangumi/play/ep70133"}]},{"id":11706,"name":"女帝謁見","sites":[{"site":"bilibili","title":"谒见女皇","url":"https://www.bilibili.com/bangumi/play/ep70134"}]},{"id":11707,"name":"愛人たち","sites":[{"site":"bilibili","title":"爱人们","url":"https://www.bilibili.com/bangumi/play/ep70135"}]},{"id":11708,"name":"王家の詩","sites":[{"site":"bilibili","title":"皇家之诗","url":"https://www.bilibili.com/bangumi/play/ep70063"}]},{"id":11709,"name":"聖都の雨","sites":[{"site":"bilibili","title":"圣都之雨","url":"https://www.bilibili.com/bangumi/play/ep70113"}]},{"id":11710,"name":"祖国に眠れ","sites":[{"site":"bilibili","title":"祖国之眠","url":"https://www.bilibili.com/bangumi/play/ep70138"}]},{"id":11711,"name":"兆し","sites":[{"site":"bilibili","title":"预兆","url":"https://www.bilibili.com/bangumi/play/ep70067"}]},{"id":11712,"name":"ロバート・ウッドの鞄","sites":[{"site":"bilibili","title":"罗伯特·伍德的公事包","url":"https://www.bilibili.com/bangumi/play/ep70174"}]},{"id":11713,"name":"最後の密命","sites":[{"site":"bilibili","title":"最后的密令","url":"https://www.bilibili.com/bangumi/play/ep70118"}]},{"id":11714,"name":"魂の行方","sites":[{"site":"bilibili","title":"魂的去向","url":"https://www.bilibili.com/bangumi/play/ep70142"}]},{"id":11715,"name":"メドメナムの地","sites":[{"site":"bilibili","title":"一个名叫梅多梅那姆的地方","url":"https://www.bilibili.com/bangumi/play/ep70143"}]},{"id":11716,"name":"新世界","sites":[{"site":"bilibili","title":"新世界","url":"https://www.bilibili.com/bangumi/play/ep70096"}]},{"id":11717,"name":"紅に染むるまで","sites":[{"site":"bilibili","title":"直到红色鲜血流尽","url":"https://www.bilibili.com/bangumi/play/ep70049"}]},{"id":11718,"name":"殉ずるものと","sites":[{"site":"bilibili","title":"牺牲自己","url":"https://www.bilibili.com/bangumi/play/ep70050"}]},{"id":11719,"name":"名誉の代償","sites":[{"site":"bilibili","title":"名誉的代价","url":"https://www.bilibili.com/bangumi/play/ep70124"}]},{"id":11720,"name":"NQM","sites":[{"site":"bilibili","title":"NQM","url":"https://www.bilibili.com/bangumi/play/ep70125"}]},{"id":11721,"name":"最愛なる――ゆえに","sites":[{"site":"bilibili","title":"为了挚爱","url":"https://www.bilibili.com/bangumi/play/ep70126"}]},{"id":11722,"name":"言葉ありき","sites":[{"site":"bilibili","title":"太初有道","url":"https://www.bilibili.com/bangumi/play/ep70127"}]}]}