{"id":"234305","name":"鬼灯の冷徹 第弐期その弐","eps":[{"id":787635,"name":"閻魔庁の日々／一汁三菜十肉","sites":[{"site":"bilibili","title":"阎魔厅的日常 / 一汤三菜十肉","url":"https://www.bilibili.com/bangumi/play/ep200358"}]},{"id":787636,"name":"魔女っ娘とはなんぞや／洋装道楽","sites":[{"site":"bilibili","title":"何为小魔女 / 洋装之趣","url":"https://www.bilibili.com/bangumi/play/ep200359"}]},{"id":787637,"name":"お迎え課の荼吉尼／草葉の陰","sites":[{"site":"bilibili","title":"迎接科的荼吉尼 / 草叶的背后","url":"https://www.bilibili.com/bangumi/play/ep200360"}]},{"id":787638,"name":"妖怪に学んだ男と妖怪を使う女","sites":[{"site":"bilibili","title":"师从妖怪的男人与操纵妖怪的女人","url":"https://www.bilibili.com/bangumi/play/ep200361"}]},{"id":787639,"name":"天邪鬼／帰れ鶴","sites":[{"site":"bilibili","title":"天邪鬼 / 滚吧 仙鹤","url":"https://www.bilibili.com/bangumi/play/ep200362"}]},{"id":787640,"name":"瓢箪鯰／檎働く","sites":[{"site":"bilibili","title":"秃瓢鲶鱼 / 阿檎开工","url":"https://www.bilibili.com/bangumi/play/ep200363"}]},{"id":787641,"name":"ゲーム／絡繰補佐官","sites":[{"site":"bilibili","title":"游戏 / 人偶辅佐官","url":"https://www.bilibili.com/bangumi/play/ep200364"}]},{"id":787642,"name":"芥子という兎／範疇","sites":[{"site":"bilibili","title":"芥子这只兔 / 范畴","url":"https://www.bilibili.com/bangumi/play/ep200365"}]},{"id":787643,"name":"野干兄妹／シロの尻が大ピンチ","sites":[{"site":"bilibili","title":"野干兄妹 / 小白的菊花危机","url":"https://www.bilibili.com/bangumi/play/ep200366"}]},{"id":787644,"name":"こんぽんてきに／異種格闘技戦","sites":[{"site":"bilibili","title":"根本问题 / 异种格斗技能大战","url":"https://www.bilibili.com/bangumi/play/ep200367"}]},{"id":787645,"name":"奪衣婆と懸衣翁／お料理ミキちゃん","sites":[{"site":"bilibili","title":"夺衣婆和悬衣翁 / 美纪下厨","url":"https://www.bilibili.com/bangumi/play/ep200368"}]},{"id":787646,"name":"瘟鬼／動物は恩を忘れない","sites":[{"site":"bilibili","title":"瘟鬼 / 动物绝不会忘恩负义","url":"https://www.bilibili.com/bangumi/play/ep200369"}]},{"id":787647,"name":"ポーカーなら無敵／逝き先はじゅごくの方で宜しかったでしょうか？","sites":[{"site":"bilibili","title":"扑克无敌 / 前方乃地狱 君愿前往？","url":"https://www.bilibili.com/bangumi/play/ep200370"}]}]}