{"id":"25602","name":"地獄先生ぬ～べ～","sites":[{"site":"iqiyi","id":"a_19rrhb1b39","sort":49}],"eps":[{"id":128965,"sort":1,"name":"恐怖の新学期!謎の鬼の手","sites":[{"site":"iqiyi","sort":1,"title":"恐怖的新学期！ 神秘的鬼手","url":"http://www.iqiyi.com/v_19rronhqxs.html","time":"2015-08-14T16:01:19.000Z"}]},{"id":128966,"sort":2,"name":"トイレの花子さんが出たぁ〜っ!","sites":[{"site":"iqiyi","sort":2,"title":"厕所里的花子小姐出现了！","url":"http://www.iqiyi.com/v_19rronhqqc.html","time":"2015-08-14T16:01:19.000Z"}]},{"id":128967,"sort":3,"name":"うわさ話はやめられない!おしゃべり妖怪・恐怖の五枚舌!","sites":[{"site":"iqiyi","sort":3,"title":"无法停止传播闲话！八卦的妖怪▪恐怖的五舌妖","url":"http://www.iqiyi.com/v_19rronhthc.html","time":"2015-08-14T16:01:19.000Z"}]},{"id":128968,"sort":4,"name":"使用禁止!?河童の出る鉄棒","sites":[{"site":"iqiyi","sort":4,"title":"禁止使用！？出现河童的单杠","url":"http://www.iqiyi.com/v_19rronht3g.html","time":"2015-08-14T16:01:19.000Z"}]},{"id":128969,"sort":5,"name":"学校の七不思議魔の13階段","sites":[{"site":"iqiyi","sort":5,"title":"学校的七不可思议 魔之第十三阶梯","url":"http://www.iqiyi.com/v_19rronhstk.html","time":"2015-08-14T16:01:19.000Z"}]},{"id":128970,"sort":6,"name":"ぬ〜べ〜死す!?最強の敵（ライバル）・妖狐玉藻","sites":[{"site":"iqiyi","sort":6,"title":"阿鵺 死去！？最强的敌人妖狐玉藻","url":"http://www.iqiyi.com/v_19rronhva0.html","time":"2015-08-14T16:01:25.000Z"}]},{"id":128971,"sort":7,"name":"鬼の手VS火輪尾の術","sites":[{"site":"iqiyi","sort":7,"title":"鬼手VS火轮尾之术","url":"http://www.iqiyi.com/v_19rronhuto.html","time":"2015-08-14T16:01:31.000Z"}]},{"id":128972,"sort":8,"name":"UFO襲来!宇宙人童守町に現る","sites":[{"site":"iqiyi","sort":8,"title":"UFO袭来！宇宙人出现在童守町","url":"http://www.iqiyi.com/v_19rronhudw.html","time":"2015-08-14T16:01:28.000Z"}]},{"id":128973,"sort":9,"name":"5年3組大パニック!巨乳ろくろ首","sites":[{"site":"iqiyi","sort":9,"title":"五年三班大恐慌！巨乳长颈妖","url":"http://www.iqiyi.com/v_19rronhtz4.html","time":"2015-08-14T16:01:22.000Z"}]},{"id":128974,"sort":10,"name":"悪鬼大暴れ!努力する子はご用心","sites":[{"site":"iqiyi","sort":10,"title":"恶鬼大暴动！努力的孩子要小心","url":"http://www.iqiyi.com/v_19rronhk88.html","time":"2015-08-14T16:01:22.000Z"}]},{"id":128975,"sort":11,"name":"スクープ!ぬ〜べ〜が雪女と婚約!?","sites":[{"site":"iqiyi","sort":11,"title":"独家新闻！神眉与雪女婚约！？","url":"http://www.iqiyi.com/v_19rronhk0s.html","time":"2015-08-14T16:01:26.000Z"}]},{"id":128976,"sort":12,"name":"恐怖の遠足!鬼門峠の謎","sites":[{"site":"iqiyi","sort":12,"title":"恐怖的远足！鬼门山之谜","url":"http://www.iqiyi.com/v_19rronhjv8.html","time":"2015-08-14T16:01:26.000Z"}]},{"id":128977,"sort":13,"name":"教室が凶器に変身!?妖刀はたもんばの呪い","sites":[{"site":"iqiyi","sort":13,"title":"教室变身凶器！？妖刀幡门场的诅咒","url":"http://www.iqiyi.com/v_19rronhjm0.html","time":"2015-08-14T16:01:28.000Z"}]},{"id":128978,"sort":14,"name":"郷子が2人!?ドッペルゲンガーの恐怖","sites":[{"site":"iqiyi","sort":14,"title":"有两个乡子！？分身的恐怖","url":"http://www.iqiyi.com/v_19rronhjgg.html","time":"2015-08-14T16:01:35.000Z"}]},{"id":128979,"sort":15,"name":"ゆきめリターンズ!真夏の冷凍大作戦","sites":[{"site":"iqiyi","sort":15,"title":"雪女回来了！盛夏的冰冻大作战","url":"http://www.iqiyi.com/v_19rronhj90.html","time":"2015-08-14T16:01:22.000Z"}]},{"id":128980,"sort":16,"name":"鬼の手使用不能!!旧校舎の怪人","sites":[{"site":"iqiyi","sort":16,"title":"鬼手使用不能！！旧校舍的怪","url":"http://www.iqiyi.com/v_19rronhlr0.html","time":"2015-08-14T16:01:31.000Z"}]},{"id":128981,"sort":17,"name":"プールサイドのロマンス…第4コースの幽霊","sites":[{"site":"iqiyi","sort":17,"title":"泳池畔的罗曼史…第四水道的幽灵","url":"http://www.iqiyi.com/v_19rronhlsk.html","time":"2015-08-14T16:01:31.000Z"}]},{"id":128982,"sort":18,"name":"復活の妖狐（ライバル）・玉藻!校庭に潜む巨大怪魚!!","sites":[{"site":"iqiyi","sort":18,"title":"复活的妖狐玉藻！潜伏在校园的巨大怪鱼！！","url":"http://www.iqiyi.com/v_19rronhlm4.html","time":"2015-08-14T16:01:31.000Z"}]},{"id":128983,"sort":19,"name":"連続切り裂き魔!最強ペア愛の大追跡!!","sites":[{"site":"iqiyi","sort":19,"title":"连续劈人魔！最强情侣爱的大追击！！","url":"http://www.iqiyi.com/v_19rronhlgk.html","time":"2015-08-14T16:01:31.000Z"}]},{"id":128984,"sort":20,"name":"過去へのタイムスリップ!見たぞぬ〜べ〜の秘密!!","sites":[{"site":"iqiyi","sort":20,"title":"回到过去的时间穿越！看到了 阿鵺的秘密！！","url":"http://www.iqiyi.com/v_19rronhl4s.html","time":"2015-08-14T16:01:27.000Z"}]},{"id":128985,"sort":21,"name":"神との激突!裁きを受けるのは俺だ!!","sites":[{"site":"iqiyi","sort":21,"title":"与神的激斗！要受制裁的人是我！！","url":"http://www.iqiyi.com/v_19rronhl94.html","time":"2015-08-14T16:01:29.000Z"}]},{"id":128986,"sort":22,"name":"君のうしろに誰かいる!恐怖の心霊写真!!","sites":[{"site":"iqiyi","sort":22,"title":"谁在你后面！恐怖的灵异照片！！","url":"http://www.iqiyi.com/v_19rronhkzw.html","time":"2015-08-14T16:01:33.000Z"}]},{"id":128987,"sort":23,"name":"0時0分0秒の怪!?合わせ鏡の七不思議","sites":[{"site":"iqiyi","sort":23,"title":"零时零分零秒之怪！？对照镜的七个不可思议","url":"http://www.iqiyi.com/v_19rronhkkg.html","time":"2015-08-14T16:01:30.000Z"}]},{"id":128988,"sort":24,"name":"魔性のDカップ!!愛のカラス伝説","sites":[{"site":"iqiyi","sort":24,"title":"魔性的D罩杯！！恩爱的乌鸦传说","url":"http://www.iqiyi.com/v_19rronhncc.html","time":"2015-08-14T16:01:32.000Z"}]},{"id":128989,"sort":25,"name":"しあわせパニック!涙に消えた座敷わらし","sites":[{"site":"iqiyi","sort":25,"title":"幸福的恐慌！在泪眼中消失的座敷童子","url":"http://www.iqiyi.com/v_19rronhn40.html","time":"2015-08-14T16:01:28.000Z"}]},{"id":128990,"sort":26,"name":"戦慄の2世誕生!!ママは妖怪、パパは先生!","sites":[{"site":"iqiyi","sort":26,"title":"战栗的第2代诞生！！妈妈是妖怪 爸爸是老师！","url":"http://www.iqiyi.com/v_19rronhn98.html","time":"2015-08-14T16:01:31.000Z"}]},{"id":128991,"sort":27,"name":"コギャルの危険なアルバイト!?霊獣を操る美少女いずな","sites":[{"site":"iqiyi","sort":27,"title":"小女孩的危险打工！？操纵灵兽的美少女东名","url":"http://www.iqiyi.com/v_19rronhmro.html","time":"2015-08-14T16:01:31.000Z"}]},{"id":128992,"sort":28,"name":"世にも奇妙なXマス…幸せのケサランパサラン","sites":[{"site":"iqiyi","sort":28,"title":"世间奇妙的圣诞节…带来幸运的雪花球","url":"http://www.iqiyi.com/v_19rronhmn0.html","time":"2015-08-14T16:01:34.000Z"}]},{"id":128993,"sort":29,"name":"妖怪オールスター総登場!呪われた学園祭!!","sites":[{"site":"iqiyi","sort":29,"title":"妖怪全明星总登场！被诅咒的学园祭！！","url":"http://www.iqiyi.com/v_19rronhm3w.html","time":"2015-08-14T16:01:29.000Z"}]},{"id":128994,"sort":30,"name":"放課後の恐怖!走る二宮金次郎像!!","sites":[{"site":"iqiyi","sort":30,"title":"放学后的恐怖！奔跑的二宫金次郎像！！","url":"http://www.iqiyi.com/v_19rronhowo.html","time":"2015-08-14T16:01:31.000Z"}]},{"id":128995,"sort":31,"name":"誰にも言えない目玉の恐怖!!天才バイオリニストの大罪","sites":[{"site":"iqiyi","sort":31,"title":"说不出的恐怖眼珠！！天才小提琴家的大罪","url":"http://www.iqiyi.com/v_19rromnnao.html","time":"2015-08-14T16:01:46.000Z"}]},{"id":128996,"sort":32,"name":"そして誰もいなくなる!図書室の赤い怪少女!!（アニメオリジナル）","sites":[{"site":"iqiyi","sort":32,"title":"大家都不见了！图书室里的红毛衣怪少女！！","url":"http://www.iqiyi.com/v_19rronhoy8.html","time":"2015-08-14T16:01:31.000Z"}]},{"id":128997,"sort":33,"name":"しょうけらが窓からのぞく!リツコ先生最大の危機!!","sites":[{"site":"iqiyi","sort":33,"title":"在窗外偷窥的怪物！律子老师的最大危机！！","url":"http://www.iqiyi.com/v_19rronhors.html","time":"2015-08-14T16:01:28.000Z"}]},{"id":128998,"sort":34,"name":"今明かされる禁断の過去!鬼の手誕生の秘密!!","sites":[{"site":"iqiyi","sort":34,"title":"被揭晓的禁断的过去！鬼手诞生的秘密！！","url":"http://www.iqiyi.com/v_19rronhom8.html","time":"2015-08-14T16:01:31.000Z"}]},{"id":128999,"sort":35,"name":"ダイダラボッチは私の虜!美樹ちゃんのドリームタウン!!","sites":[{"site":"iqiyi","sort":35,"title":"大太法师是我的奴隶！美树的梦想成真！！","url":"http://www.iqiyi.com/v_19rronho4w.html","time":"2015-08-14T16:01:31.000Z"}]},{"id":129000,"sort":36,"name":"真夜中の㊙レッスン!音楽室の危険な誘惑!!（アニメオリジナル）","sites":[{"site":"iqiyi","sort":36,"title":"深夜的秘密课程！音乐教室危险的诱惑！！","url":"http://www.iqiyi.com/v_19rronho00.html","time":"2015-08-14T16:01:31.000Z"}]},{"id":129001,"sort":37,"name":"20年前の忘れ物!?血に染まった予言ノート!!","sites":[{"site":"iqiyi","sort":37,"title":"20年前遗忘的物品? 染血的预言笔记本!!","url":"http://www.iqiyi.com/v_19rronhduw.html","time":"2015-08-14T16:01:37.000Z"}]},{"id":129002,"sort":38,"name":"エッ!ライバルが初デート?ゆきめの熱くて長い一日!!","sites":[{"site":"iqiyi","sort":38,"title":"诶！ 情敌的第一次约会？雪女又热又长的一天！！","url":"http://www.iqiyi.com/v_19rronhds4.html","time":"2015-08-14T16:01:40.000Z"}]},{"id":129003,"sort":39,"name":"死の底からの復讐!出るか?鬼と妖狐の合体奥義!!","sites":[{"site":"iqiyi","sort":39,"title":"从死亡谷底而来的复仇！会出现吗？恶鬼与妖狐的合体绝招！！","url":"http://www.iqiyi.com/v_19rronhdng.html","time":"2015-08-14T16:01:40.000Z"}]},{"id":129004,"sort":40,"name":"セーラー服が燃えちゃう!隠しきれない、いずなのハート!!","sites":[{"site":"iqiyi","sort":40,"title":"水手服燃烧起来了！无法隐藏的东名的热情！！","url":"http://www.iqiyi.com/v_19rronhdp0.html","time":"2015-08-14T16:01:37.000Z"}]},{"id":129005,"sort":41,"name":"トモダチニナリタイ…謎の同級生、戦慄の正体!!","sites":[{"site":"iqiyi","sort":41,"title":"我想要跟你们做朋友…神秘的同学 可怕的真面目！！","url":"http://www.iqiyi.com/v_19rronhd8o.html","time":"2015-08-14T16:01:37.000Z"}]},{"id":129006,"sort":42,"name":"母ちゃんは4歳児!?嵐を呼ぶ前世の記憶!!","sites":[{"site":"iqiyi","sort":42,"title":"妈妈是四岁小孩！？暴风雨呼唤来的前世记忆！！","url":"http://www.iqiyi.com/v_19rronhdd0.html","time":"2015-08-14T16:01:40.000Z"}]},{"id":129007,"sort":43,"name":"ゆきめ死す!!愛は雪の結晶と消えて…","sites":[{"site":"iqiyi","sort":43,"title":"雪姬之死！！爱化为雪的结晶消失了…","url":"http://www.iqiyi.com/v_19rronhcvo.html","time":"2015-08-14T16:01:37.000Z"}]},{"id":129008,"sort":44,"name":"子どもは見ちゃダメ!!禁断の怪談・百物語","sites":[{"site":"iqiyi","sort":44,"title":"小孩子不要看！！禁忌怪谈一百鬼话","url":"http://www.iqiyi.com/v_19rronhcwc.html","time":"2015-08-14T16:01:36.000Z"}]},{"id":129009,"sort":45,"name":"夢?幻?復活のゆきめ恋人よ、なぜ俺の命を狙う!!","sites":[{"site":"iqiyi","sort":45,"title":"梦境还是幻觉？复活的雪姬 爱人啊 为什么要取我性命呢！！","url":"http://www.iqiyi.com/v_19rronhcmg.html","time":"2015-08-14T16:05:40.000Z"}]},{"id":129010,"sort":46,"name":"狙われたヒロインたち!ドキドキおふろパニック!!","sites":[{"site":"iqiyi","sort":46,"title":"被盯上的女主角们！紧张刺激的澡堂骚乱！！","url":"http://www.iqiyi.com/v_19rronhcgw.html","time":"2015-08-14T16:01:35.000Z"}]},{"id":129011,"sort":47,"name":"最強!最大!最後の敵その名は…貧乏神!!","sites":[{"site":"iqiyi","sort":47,"title":"最强！最大！最后的敌人 名为…贫穷之神！！","url":"http://www.iqiyi.com/v_19rronhfjk.html","time":"2015-08-14T16:01:46.000Z"}]},{"id":129012,"sort":48,"name":"夢をいつまでも!!大好きな僕らのぬ〜べ〜!","sites":[{"site":"iqiyi","sort":48,"title":"梦想会永远持续！！我们最喜欢的阿鵺！","url":"http://www.iqiyi.com/v_19rronhf60.html","time":"2015-08-14T16:01:46.000Z"}]},{"id":129013,"sort":49,"name":"完全保存版!!地獄先生ぬ〜べ〜超百科","sites":[{"site":"iqiyi","sort":49,"title":"完全保存版！！地狱老师阿鵺超百科","url":"http://www.iqiyi.com/v_19rronhf2w.html","time":"2015-08-14T16:01:46.000Z"}]}]}