{"id":"74628","name":"ニセコイ","sites":[{"site":"bilibili","id":"28227496","sort":20}],"eps":[{"id":350237,"sort":1,"name":"ヤクソク","sites":[{"site":"bilibili","sort":1,"title":"约定","url":"https://www.bilibili.com/bangumi/play/ep29064","time":"2014-01-11T14:34:00.000Z"}]},{"id":350238,"sort":2,"name":"ソウグウ","sites":[{"site":"bilibili","sort":2,"title":"遭遇","url":"https://www.bilibili.com/bangumi/play/ep29063","time":"2014-01-18T14:37:00.000Z"}]},{"id":350239,"sort":3,"name":"ニタモノ","sites":[{"site":"bilibili","sort":3,"title":"相似之物","url":"https://www.bilibili.com/bangumi/play/ep29062","time":"2014-01-26T02:53:00.000Z"}]},{"id":350240,"sort":4,"name":"ホウモン","sites":[{"site":"bilibili","sort":4,"title":"访问","url":"https://www.bilibili.com/bangumi/play/ep29061","time":"2014-02-02T07:32:00.000Z"}]},{"id":350241,"sort":5,"name":"スイエイ","sites":[{"site":"bilibili","sort":5,"title":"游泳","url":"https://www.bilibili.com/bangumi/play/ep29060","time":"2014-02-09T02:58:00.000Z"}]},{"id":350242,"sort":6,"name":"カシカリ","sites":[{"site":"bilibili","sort":6,"title":"借与还","url":"https://www.bilibili.com/bangumi/play/ep29059","time":"2014-02-16T02:46:00.000Z"}]},{"id":350243,"sort":7,"name":"ライバル","sites":[{"site":"bilibili","sort":7,"title":"对手","url":"https://www.bilibili.com/bangumi/play/ep29058","time":"2014-02-22T14:40:00.000Z"}]},{"id":350244,"sort":8,"name":"シアワセ","sites":[{"site":"bilibili","sort":8,"title":"幸福","url":"https://www.bilibili.com/bangumi/play/ep29057","time":"2014-03-01T14:38:00.000Z"}]},{"id":350245,"sort":9,"name":"オンセン","sites":[{"site":"bilibili","sort":9,"title":"温泉","url":"https://www.bilibili.com/bangumi/play/ep29056","time":"2014-03-08T14:44:00.000Z"}]},{"id":350246,"sort":10,"name":"クジビキ","sites":[{"site":"bilibili","sort":10,"title":"抽签","url":"https://www.bilibili.com/bangumi/play/ep29055","time":"2014-03-15T14:39:00.000Z"}]},{"id":350247,"sort":11,"name":"オイワイ","sites":[{"site":"bilibili","sort":11,"title":"庆祝","url":"https://www.bilibili.com/bangumi/play/ep29054","time":"2014-03-22T14:38:00.000Z"}]},{"id":350248,"sort":12,"name":"カクニン","sites":[{"site":"bilibili","sort":12,"title":"确认","url":"https://www.bilibili.com/bangumi/play/ep29053","time":"2014-03-29T14:39:00.000Z"}]},{"id":350249,"sort":13,"name":"ホウカゴ","sites":[{"site":"bilibili","sort":13,"title":"放学后","url":"https://www.bilibili.com/bangumi/play/ep29052","time":"2014-04-05T14:55:00.000Z"}]},{"id":350250,"sort":14,"name":"シュラバ","sites":[{"site":"bilibili","sort":14,"title":"修罗场","url":"https://www.bilibili.com/bangumi/play/ep29051","time":"2014-04-12T14:38:00.000Z"}]},{"id":350251,"sort":15,"name":"サンボン","sites":[{"site":"bilibili","sort":15,"title":"三把钥匙","url":"https://www.bilibili.com/bangumi/play/ep29050","time":"2014-04-19T14:45:00.000Z"}]},{"id":350252,"sort":16,"name":"タイフウ","sites":[{"site":"bilibili","sort":16,"title":"台风","url":"https://www.bilibili.com/bangumi/play/ep29049","time":"2014-04-26T14:38:00.000Z"}]},{"id":350253,"sort":17,"name":"エンニチ","sites":[{"site":"bilibili","sort":17,"title":"庙会","url":"https://www.bilibili.com/bangumi/play/ep29048","time":"2014-05-03T14:39:00.000Z"}]},{"id":350254,"sort":18,"name":"ウミベデ","sites":[{"site":"bilibili","sort":18,"title":"海边","url":"https://www.bilibili.com/bangumi/play/ep29047","time":"2014-05-10T15:03:00.000Z"}]},{"id":350255,"sort":19,"name":"エンゲキ","sites":[{"site":"bilibili","sort":19,"title":"戏剧","url":"https://www.bilibili.com/bangumi/play/ep29046","time":"2014-05-17T14:34:00.000Z"}]},{"id":350256,"sort":20,"name":"ホソバソ","sites":[{"site":"bilibili","sort":20,"title":"实演","url":"https://www.bilibili.com/bangumi/play/ep29045","time":"2014-05-24T14:38:00.000Z"}]}]}