{"id":"89488","name":"うたの☆プリンスさまっ♪ マジLOVEレボリューションズ","eps":[{"id":512883,"name":"The dice are cast","sites":[{"site":"bilibili","title":"The dice are cast","url":"https://www.bilibili.com/bangumi/play/ep28946"},{"site":"qq","title":"第01话 The dice are cast","url":"http://v.youku.com/v_show/id_XOTI3MDc4MDA4.html?from=y1.6-100.3.1.efa80170d20611e4b432"},{"site":"youku","sort":"1","title":"第01话 The dice are cast","url":"https://v.youku.com/v_show/id_XOTI3MDc4MDA4"}],"sort":1},{"id":512884,"name":"GOLDEN★STAR","sites":[{"site":"bilibili","title":"Golden★Star","url":"https://www.bilibili.com/bangumi/play/ep29111"},{"site":"qq","title":"第02话 Golden star","url":"http://v.youku.com/v_show/id_XOTMxOTA2NTMy.html?from=y1.6-100.3.1.efa80170d20611e4b432"},{"site":"youku","sort":"2","title":"第02话 Golden star","url":"https://v.youku.com/v_show/id_XOTMxOTA2NTMy"}],"sort":2},{"id":512885,"name":"EMOTIONAL LIFE","sites":[{"site":"bilibili","title":"Emotional Life","url":"https://www.bilibili.com/bangumi/play/ep29980"},{"site":"qq","title":"第03话 Emotional life","url":"http://v.youku.com/v_show/id_XOTM2ODQ5Mjcy.html?from=y1.6-100.3.1.efa80170d20611e4b432"},{"site":"youku","sort":"3","title":"第03话 Emotional life","url":"https://v.youku.com/v_show/id_XOTM2ODQ5Mjcy"}],"sort":3},{"id":512886,"name":"Innocent Wind","sites":[{"site":"bilibili","title":"Innocent Wind","url":"https://www.bilibili.com/bangumi/play/ep35272"},{"site":"qq","title":"第04话 Innocent wind","url":"http://v.youku.com/v_show/id_XOTQxODc4Mzk2.html?from=y1.6-100.3.1.efa80170d20611e4b432"},{"site":"youku","sort":"4","title":"第04话 Innocent wind","url":"https://v.youku.com/v_show/id_XOTQxODc4Mzk2"}],"sort":4},{"id":512887,"name":"Code:T.V.U","sites":[{"site":"bilibili","title":"Code:T.V.U","url":"https://www.bilibili.com/bangumi/play/ep36319"},{"site":"qq","title":"第05话 Code:T.V.U","url":"http://v.youku.com/v_show/id_XOTQ2Nzg2ODg0.html?from=y1.6-100.3.1.efa80170d20611e4b432"},{"site":"youku","sort":"5","title":"第05话 Code:T.V.U","url":"https://v.youku.com/v_show/id_XOTQ2Nzg2ODg0"}],"sort":5},{"id":512888,"name":"Saintly Territory","sites":[{"site":"bilibili","title":"Saintly Territory","url":"https://www.bilibili.com/bangumi/play/ep45746"},{"site":"qq","title":"第06话 Saintly Territory","url":"http://v.youku.com/v_show/id_XOTUxOTY5NjEy.html?from=y1.6-100.3.1.efa80170d20611e4b432"},{"site":"youku","sort":"6","title":"第06话 Saintly Territory","url":"https://v.youku.com/v_show/id_XOTUxOTY5NjEy"}],"sort":6},{"id":512889,"name":"ONLY ONE","sites":[{"site":"bilibili","title":"Only One","url":"https://www.bilibili.com/bangumi/play/ep54245"},{"site":"qq","title":"第07话 Only one","url":"http://v.youku.com/v_show/id_XOTU3MzczOTMy.html?from=y1.6-100.3.1.efa80170d20611e4b432"},{"site":"youku","sort":"7","title":"第07话 Only one","url":"https://v.youku.com/v_show/id_XOTU3MzczOTMy"}],"sort":7},{"id":512890,"name":"ORIGINAL RESONANCE","sites":[{"site":"bilibili","title":"Original Resonance","url":"https://www.bilibili.com/bangumi/play/ep62410"},{"site":"qq","title":"第08话 Original Resonance","url":"http://v.youku.com/v_show/id_XOTYyNjE2OTY0.html?from=y1.6-100.3.1.efa80170d20611e4b432"},{"site":"youku","sort":"8","title":"第08话 Original Resonance","url":"https://v.youku.com/v_show/id_XOTYyNjE2OTY0"}],"sort":8},{"id":512891,"name":"NEVER♪♪♪","sites":[{"site":"bilibili","title":"Never♪♪♪","url":"https://www.bilibili.com/bangumi/play/ep62690"},{"site":"qq","title":"第09话 Never","url":"http://v.youku.com/v_show/id_XMTI0OTg4ODQ2OA==.html?from=y1.6-100.3.1.efa80170d20611e4b432"},{"site":"youku","sort":"9","title":"第09话 Never","url":"https://v.youku.com/v_show/id_XMTI0OTg4ODQ2OA=="}],"sort":9},{"id":512892,"name":"Answer","sites":[{"site":"bilibili","title":"Answer","url":"https://www.bilibili.com/bangumi/play/ep62748"},{"site":"qq","title":"第10话 Answer","url":"http://v.youku.com/v_show/id_XMTI1NjU1MDkyNA==.html?from=y1.6-100.3.1.efa80170d20611e4b432"},{"site":"youku","sort":"10","title":"第10话 Answer","url":"https://v.youku.com/v_show/id_XMTI1NjU1MDkyNA=="}],"sort":10},{"id":512893,"name":"サンキュ（Thank you）","sites":[{"site":"bilibili","title":"Thank you","url":"https://www.bilibili.com/bangumi/play/ep62858"},{"site":"qq","title":"第11话 Thank You","url":"http://v.youku.com/v_show/id_XMTI2MTg3NDA4NA==.html?from=y1.6-100.3.1.efa80170d20611e4b432"},{"site":"youku","sort":"11","title":"第11话 Thank You","url":"https://v.youku.com/v_show/id_XMTI2MTg3NDA4NA=="}],"sort":11},{"id":512894,"name":"エボリューション・イヴ（Evolution·Eve）","sites":[{"site":"bilibili","title":"Evolution·Eve","url":"https://www.bilibili.com/bangumi/play/ep63588"},{"site":"qq","title":"第12话 Evolution·eve","url":"http://v.youku.com/v_show/id_XMTI2NjkwMjAyNA==.html?from=y1.6-100.3.1.efa80170d20611e4b432"},{"site":"youku","sort":"12","title":"第12话 Evolution·eve","url":"https://v.youku.com/v_show/id_XMTI2NjkwMjAyNA=="}],"sort":12},{"id":534641,"name":"マジLOVEレボリューションズ","sites":[{"site":"bilibili","title":"真爱Revolutions","url":"https://www.bilibili.com/bangumi/play/ep63733"},{"site":"qq","title":"第13话 真爱Revolutions","url":"http://v.youku.com/v_show/id_XMTI3MjA0NTQ2NA==.html?from=y1.6-100.3.1.efa80170d20611e4b432"},{"site":"youku","sort":"13","title":"第13话 真爱Revolutions","url":"https://v.youku.com/v_show/id_XMTI3MjA0NTQ2NA=="}],"sort":13}]}