{
 "id": "68031",
 "name": "ゴールデンタイム",
 "sites": [
  {
   "site": "bilibili",
   "id": "468",
   "sort": 24
  }
 ],
 "eps": [
  {
   "id": 319380,
   "sort": 1,
   "name": "スプリングタイム",
   "sites": [
    {
     "site": "bilibili",
     "sort": 1,
     "title": "春日时光",
     "url": "https://www.bilibili.com/bangumi/play/ep8728",
     "time": "2013-10-03T21:25:00.000Z"
    }
   ]
  },
  {
   "id": 319381,
   "sort": 2,
   "name": "ロンリーガール",
   "sites": [
    {
     "site": "bilibili",
     "sort": 2,
     "title": "孤单女孩",
     "url": "https://www.bilibili.com/bangumi/play/ep8727",
     "time": "2013-10-10T18:36:00.000Z"
    }
   ]
  },
  {
   "id": 319382,
   "sort": 3,
   "name": "ナイトエスケープ",
   "sites": [
    {
     "site": "bilibili",
     "sort": 3,
     "title": "夜晚逃离",
     "url": "https://www.bilibili.com/bangumi/play/ep8726",
     "time": "2013-10-17T18:42:00.000Z"
    }
   ]
  },
  {
   "id": 319383,
   "sort": 4,
   "name": "ブラックアウト",
   "sites": [
    {
     "site": "bilibili",
     "sort": 4,
     "title": "暗中隐匿",
     "url": "https://www.bilibili.com/bangumi/play/ep8725",
     "time": "2013-10-24T18:35:00.000Z"
    }
   ]
  },
  {
   "id": 319384,
   "sort": 5,
   "name": "ボディ・アンド・ソウル",
   "sites": [
    {
     "site": "bilibili",
     "sort": 5,
     "title": "身体和灵魂",
     "url": "https://www.bilibili.com/bangumi/play/ep8724",
     "time": "2013-10-31T18:59:00.000Z"
    }
   ]
  },
  {
   "id": 319385,
   "sort": 6,
   "name": "イエス・ノー",
   "sites": [
    {
     "site": "bilibili",
     "sort": 6,
     "title": "Yes・No",
     "url": "https://www.bilibili.com/bangumi/play/ep8723",
     "time": "2013-11-07T18:36:00.000Z"
    }
   ]
  },
  {
   "id": 319386,
   "sort": 7,
   "name": "マスカレード",
   "sites": [
    {
     "site": "bilibili",
     "sort": 7,
     "title": "假面舞会",
     "url": "https://www.bilibili.com/bangumi/play/ep8722",
     "time": "2013-11-14T18:53:00.000Z"
    }
   ]
  },
  {
   "id": 319387,
   "sort": 8,
   "name": "リセット",
   "sites": [
    {
     "site": "bilibili",
     "sort": 8,
     "title": "重置",
     "url": "https://www.bilibili.com/bangumi/play/ep8721",
     "time": "2013-11-21T18:45:00.000Z"
    }
   ]
  },
  {
   "id": 319388,
   "sort": 9,
   "name": "ウィズ・ユー・アゲイン",
   "sites": [
    {
     "site": "bilibili",
     "sort": 9,
     "title": "再度相伴",
     "url": "https://www.bilibili.com/bangumi/play/ep8720",
     "time": "2013-11-28T18:43:00.000Z"
    }
   ]
  },
  {
   "id": 319389,
   "sort": 10,
   "name": "イン・ザ・ミラー",
   "sites": [
    {
     "site": "bilibili",
     "sort": 10,
     "title": "在镜中",
     "url": "https://www.bilibili.com/bangumi/play/ep8719",
     "time": "2013-12-05T18:32:00.000Z"
    }
   ]
  },
  {
   "id": 319390,
   "sort": 11,
   "name": "トラブルパーティ",
   "sites": [
    {
     "site": "bilibili",
     "sort": 11,
     "title": "麻烦派对",
     "url": "https://www.bilibili.com/bangumi/play/ep8718",
     "time": "2013-12-12T18:28:00.000Z"
    }
   ]
  },
  {
   "id": 319391,
   "sort": 12,
   "name": "ドント・ルックバック",
   "sites": [
    {
     "site": "bilibili",
     "sort": 12,
     "title": "不要回头",
     "url": "https://www.bilibili.com/bangumi/play/ep8717",
     "time": "2013-12-19T18:31:00.000Z"
    }
   ]
  },
  {
   "id": 324152,
   "sort": 13,
   "name": "サマー・ハズ・カム",
   "sites": [
    {
     "site": "bilibili",
     "sort": 13,
     "title": "夏日已至",
     "url": "https://www.bilibili.com/bangumi/play/ep8716",
     "time": "2014-01-09T18:31:00.000Z"
    }
   ]
  },
  {
   "id": 324153,
   "sort": 14,
   "name": "レイディズトーク",
   "sites": [
    {
     "site": "bilibili",
     "sort": 14,
     "title": "淑女对话",
     "url": "https://www.bilibili.com/bangumi/play/ep8715",
     "time": "2014-01-16T18:35:00.000Z"
    }
   ]
  },
  {
   "id": 324154,
   "sort": 15,
   "name": "アクシデントビーチ",
   "sites": [
    {
     "site": "bilibili",
     "sort": 15,
     "title": "意外海滩",
     "url": "https://www.bilibili.com/bangumi/play/ep8714",
     "time": "2014-01-23T18:31:00.000Z"
    }
   ]
  },
  {
   "id": 324155,
   "sort": 16,
   "name": "ウェイクアップコール",
   "sites": [
    {
     "site": "bilibili",
     "sort": 16,
     "title": "唤醒的呼叫",
     "url": "https://www.bilibili.com/bangumi/play/ep8713",
     "time": "2014-01-30T23:14:00.000Z"
    }
   ]
  },
  {
   "id": 324156,
   "sort": 17,
   "name": "リターン・トゥ・イエスタディ",
   "sites": [
    {
     "site": "bilibili",
     "sort": 17,
     "title": "回到昨天",
     "url": "https://www.bilibili.com/bangumi/play/ep8712",
     "time": "2014-02-06T18:29:00.000Z"
    }
   ]
  },
  {
   "id": 324157,
   "sort": 18,
   "name": "マイ・ホームタウン",
   "sites": [
    {
     "site": "bilibili",
     "sort": 18,
     "title": "我的家乡",
     "url": "https://www.bilibili.com/bangumi/play/ep8711",
     "time": "2014-02-13T23:44:00.000Z"
    }
   ]
  },
  {
   "id": 324158,
   "sort": 19,
   "name": "ナイト・イン・パリ",
   "sites": [
    {
     "site": "bilibili",
     "sort": 19,
     "title": "巴黎之夜",
     "url": "https://www.bilibili.com/bangumi/play/ep8710",
     "time": "2014-02-21T00:04:00.000Z"
    }
   ]
  },
  {
   "id": 324159,
   "sort": 20,
   "name": "ヒズ・キャズム",
   "sites": [
    {
     "site": "bilibili",
     "sort": 20,
     "title": "他的分歧",
     "url": "https://www.bilibili.com/bangumi/play/ep8709",
     "time": "2014-02-27T18:37:00.000Z"
    }
   ]
  },
  {
   "id": 324160,
   "sort": 21,
   "name": "アイル・ビー・バック",
   "sites": [
    {
     "site": "bilibili",
     "sort": 21,
     "title": "我会回来的",
     "url": "https://www.bilibili.com/bangumi/play/ep8708",
     "time": "2014-03-06T18:54:00.000Z"
    }
   ]
  },
  {
   "id": 324161,
   "sort": 22,
   "name": "パラダイスロスト",
   "sites": [
    {
     "site": "bilibili",
     "sort": 22,
     "title": "失乐园",
     "url": "https://www.bilibili.com/bangumi/play/ep8707",
     "time": "2014-03-13T22:33:00.000Z"
    }
   ]
  },
  {
   "id": 324162,
   "sort": 23,
   "name": "ラストスマイル",
   "sites": [
    {
     "site": "bilibili",
     "sort": 23,
     "title": "最后的微笑",
     "url": "https://www.bilibili.com/bangumi/play/ep8706",
     "time": "2014-03-21T02:56:00.000Z"
    }
   ]
  },
  {
   "id": 324163,
   "sort": 24,
   "name": "ゴールデンタイム",
   "sites": [
    {
     "site": "bilibili",
     "sort": 24,
     "title": "青春纪行",
     "url": "https://www.bilibili.com/bangumi/play/ep8705",
     "time": "2014-03-27T23:28:00.000Z"
    }
   ]
  }
 ]
}