{"id":"134390","name":"シュヴァルツェスマーケン","eps":[{"id":596914,"name":"#02","sites":[{"site":"bilibili","title":"","url":"https://www.bilibili.com/bangumi/play/ep82991"},{"site":"youku","sort":"2","title":"第02话 黑之宣告","url":"https://v.youku.com/v_show/id_XMTQ0NjA5MTUxMg=="},{"site":"iqiyi","sort":2,"title":"黑之宣告 第2集","url":"http://www.iqiyi.com/v_19rrl4ngv0.html"}],"sort":2},{"id":596915,"name":"#03","sites":[{"site":"bilibili","title":"","url":"https://www.bilibili.com/bangumi/play/ep83252"},{"site":"youku","sort":"3","title":"第03话 黑之宣告","url":"https://v.youku.com/v_show/id_XMTQ1MzM1ODg4OA=="},{"site":"iqiyi","sort":3,"title":"黑之宣告 第3集","url":"http://www.iqiyi.com/v_19rrl3j54o.html"}],"sort":3},{"id":596916,"name":"#04","sites":[{"site":"bilibili","title":"","url":"https://www.bilibili.com/bangumi/play/ep83541"},{"site":"youku","sort":"4","title":"第04话 黑之宣告","url":"https://v.youku.com/v_show/id_XMTQ1OTIyNjEzMg=="},{"site":"iqiyi","sort":4,"title":"黑之宣告 第4集","url":"http://www.iqiyi.com/v_19rrlb5yy8.html"}],"sort":4},{"id":596917,"name":"#05","sites":[{"site":"bilibili","title":"","url":"https://www.bilibili.com/bangumi/play/ep83858"},{"site":"youku","sort":"5","title":"第05话 黑之宣告","url":"https://v.youku.com/v_show/id_XMTQ2NjAzNjI3Mg=="},{"site":"iqiyi","sort":5,"title":"黑之宣告 第5集","url":"http://www.iqiyi.com/v_19rrla6vwc.html"}],"sort":5},{"id":596918,"name":"#06","sites":[{"site":"bilibili","title":"","url":"https://www.bilibili.com/bangumi/play/ep83886"},{"site":"youku","sort":"6","title":"第06话 黑之宣告","url":"https://v.youku.com/v_show/id_XMTQ3MTcxODYzMg=="},{"site":"iqiyi","sort":6,"title":"黑之宣告 第6集","url":"http://www.iqiyi.com/v_19rrl993go.html"}],"sort":6},{"id":596919,"name":"#07","sites":[{"site":"bilibili","title":"","url":"https://www.bilibili.com/bangumi/play/ep84280"},{"site":"youku","sort":"7","title":"第07话 黑之宣告","url":"https://v.youku.com/v_show/id_XMTQ3NjEzMjI3Mg=="},{"site":"iqiyi","sort":7,"title":"黑之宣告 第7集","url":"http://www.iqiyi.com/v_19rrl85avc.html"}],"sort":7},{"id":596920,"name":"#08","sites":[{"site":"bilibili","title":"","url":"https://www.bilibili.com/bangumi/play/ep84544"},{"site":"youku","sort":"8","title":"第08话 黑之宣告","url":"https://v.youku.com/v_show/id_XMTQ4MzAwMTQ1Mg=="},{"site":"iqiyi","sort":8,"title":"黑之宣告 第8集","url":"http://www.iqiyi.com/v_19rrkx24vc.html"}],"sort":8},{"id":596921,"name":"#09","sites":[{"site":"bilibili","title":"","url":"https://www.bilibili.com/bangumi/play/ep84739"},{"site":"youku","sort":"9","title":"第09话 黑之宣告","url":"https://v.youku.com/v_show/id_XMTQ4OTQ4NzMyNA=="},{"site":"iqiyi","sort":9,"title":"黑之宣告 第9集","url":"http://www.iqiyi.com/v_19rrkw3nls.html"}],"sort":9},{"id":596922,"name":"#10","sites":[{"site":"bilibili","title":"","url":"https://www.bilibili.com/bangumi/play/ep85035"},{"site":"youku","sort":"10","title":"第10话 黑之宣告","url":"https://v.youku.com/v_show/id_XMTQ5NjQ5MzAyNA=="},{"site":"iqiyi","sort":10,"title":"黑之宣告 第10集","url":"http://www.iqiyi.com/v_19rrktq850.html"}],"sort":10},{"id":596923,"name":"#11","sites":[{"site":"bilibili","title":"","url":"https://www.bilibili.com/bangumi/play/ep85231"},{"site":"youku","sort":"11","title":"第11话 黑之宣告","url":"https://v.youku.com/v_show/id_XMTUwMzc1NzkyNA=="},{"site":"iqiyi","sort":11,"title":"黑之宣告 第11集","url":"http://www.iqiyi.com/v_19rrl2o04c.html"}],"sort":11},{"id":596924,"name":"#12","sites":[{"site":"bilibili","title":"","url":"https://www.bilibili.com/bangumi/play/ep85505"},{"site":"youku","sort":"12","title":"第12话 黑之宣告","url":"https://v.youku.com/v_show/id_XMTUxMTYxMjk2MA=="},{"site":"iqiyi","sort":12,"title":"黑之宣告 第12集","url":"http://www.iqiyi.com/v_19rrl0j9hk.html"}],"sort":12},{"id":596913,"sort":1,"name":"#01","sites":[{"site":"iqiyi","sort":1,"title":"黑之宣告 第1集","url":"http://www.iqiyi.com/v_19rrl5njlo.html"}]}]}