{
 "id": "350771",
 "name": "現実主義勇者の王国再建記 第二部",
 "sites": [
  {
   "site": "bilibili",
   "id": "28234644",
   "week": 7,
   "time": "0130",
   "sort": 21
  }
 ],
 "eps": [
  {
   "id": 1072586,
   "sort": 14,
   "name": "虎の威を借るアミドニア",
   "sites": [
    {
     "site": "bilibili",
     "sort": 14,
     "title": "狐假虎威的阿米多尼亚",
     "url": "https://www.bilibili.com/bangumi/play/ep457829",
     "time": "2022-01-08T17:30:01.000Z"
    }
   ]
  },
  {
   "id": 1072587,
   "sort": 15,
   "name": "莫逆（ばくぎゃく）の友と為る",
   "sites": [
    {
     "site": "bilibili",
     "sort": 15,
     "title": "结为莫逆之交",
     "url": "https://www.bilibili.com/bangumi/play/ep457830",
     "time": "2022-01-15T17:30:01.000Z"
    }
   ]
  },
  {
   "id": 1072588,
   "sort": 16,
   "name": "苛政は寅よりも猛し",
   "sites": [
    {
     "site": "bilibili",
     "sort": 16,
     "title": "苛政猛于虎",
     "url": "https://www.bilibili.com/bangumi/play/ep457831",
     "time": "2022-01-22T17:30:01.000Z"
    }
   ]
  },
  {
   "id": 1072589,
   "sort": 17,
   "name": "士は己を知る者の為に死す",
   "sites": [
    {
     "site": "bilibili",
     "sort": 17,
     "title": "士为知己者死",
     "url": "https://www.bilibili.com/bangumi/play/ep467220",
     "time": "2022-01-29T17:30:01.000Z"
    }
   ]
  }
 ]
}